CHANGES
LICENSE
README
ez_setup.py
setup.py
doc/genhtml.py
doc/components/autohandler
doc/components/configuration.myt
doc/components/doclib.myt
doc/components/formatting.myt
doc/components/index.myt
doc/components/printsection.myt
doc/components/pydoc.myt
doc/components/section_wrapper.myt
doc/content/cache.myt
doc/content/components.myt
doc/content/docstrings.myt
doc/content/document_base.myt
doc/content/embedding.myt
doc/content/filtering.myt
doc/content/globals.myt
doc/content/inheritance.myt
doc/content/installation.myt
doc/content/modulecomponents.myt
doc/content/otherblocks.myt
doc/content/params.myt
doc/content/programmatic.myt
doc/content/request.myt
doc/content/resolver.myt
doc/content/scopedpython.myt
doc/content/session.myt
doc/content/specialtempl.myt
doc/content/technical.myt
doc/content/unicode.myt
doc/content/whatsitdo.myt
doc/html/docs.css
doc/html/style.css
doc/html/syntaxhighlight.css
doc/lib/documentgen.py
doc/lib/highlight.py
examples/favicon.ico
examples/index.myt
examples/myghty_small.png
examples/common/autohandler
examples/common/header.myc
examples/common/modulecomponents.py
examples/components/README
examples/components/autohandler
examples/components/component.myt
examples/components/index.myt
examples/formcontrols/README
examples/formcontrols/components.myt
examples/formcontrols/field.myt
examples/formcontrols/index.myt
examples/formvisitor/formfields.myc
examples/formvisitor/register.myt
examples/formvisitor/registration.myt
examples/formvisitor/lib/formvisitor.py
examples/myghtyjax/hourglass.gif
examples/myghtyjax/hourglass.myt
examples/myghtyjax/index.myt
examples/myghtyjax/myghtyjax.js
examples/myghtyjax/myghtyjax.myt
examples/myghtyjax/docs/document_base.myt
examples/myghtyjax/docs/index.myt
examples/myghtyjax/docs/intro.myt
examples/shoppingcart/run_cart.py
examples/shoppingcart/components/address.myc
examples/shoppingcart/components/autohandler
examples/shoppingcart/components/breadcrumb.myc
lib/Myghty.egg-info/PKG-INFO
lib/Myghty.egg-info/SOURCES.txt
lib/Myghty.egg-info/dependency_links.txt
lib/Myghty.egg-info/entry_points.txt
lib/Myghty.egg-info/requires.txt
lib/Myghty.egg-info/top_level.txt
