Metadata-Version: 1.0
Name: Myghty
Version: 1.2
Summary: View/Controller Framework and Templating Engine
Home-page: http://www.myghty.org
Author: Mike Bayer
Author-email: mike@myghty.org
License: MIT License
Platform: UNKNOWN
Classifier: Development Status :: 5 - Production/Stable
Classifier: Intended Audience :: Developers
Classifier: License :: OSI Approved :: MIT License
Classifier: Programming Language :: Python
Classifier: Topic :: Internet :: WWW/HTTP :: Dynamic Content
Classifier: Topic :: Text Processing :: Markup
